{"ACCD": {"rh_buy_analysts": 12, "rh_total_analysts": 12, "rh_percent_buy": 100.0}, "ACET": {"rh_buy_analysts": 7, "rh_total_analysts": 7, "rh_percent_buy": 100.0}, "ACRS": {"rh_buy_analysts": 6, "rh_total_analysts": 6, "rh_percent_buy": 100.0}, "ADUS": {"rh_buy_analysts": 7, "rh_total_analysts": 8, "rh_percent_buy": 87.5}, "AERI": {"rh_buy_analysts": 10, "rh_total_analysts": 12, "rh_percent_buy": 83.33}, "AEVA": {"rh_buy_analysts": 6, "rh_total_analysts": 7, "rh_percent_buy": 85.71}, "AGL": {"rh_buy_analysts": 9, "rh_total_analysts": 9, "rh_percent_buy": 100.0}, "AGLE": {"rh_buy_analysts": 6, "rh_total_analysts": 7, "rh_percent_buy": 85.71}, "AGTC": {"rh_buy_analysts": 9, "rh_total_analysts": 9, "rh_percent_buy": 100.0}, "AHCO": {"rh_buy_analysts": 9, "rh_total_analysts": 9, "rh_percent_buy": 100.0}, "AKRO": {"rh_buy_analysts": 7, "rh_total_analysts": 7, "rh_percent_buy": 100.0}, "AL": {"rh_buy_analysts": 8, "rh_total_analysts": 8, "rh_percent_buy": 100.0}, "ALBO": {"rh_buy_analysts": 8, "rh_total_analysts": 8, "rh_percent_buy": 100.0}, "ALDX": {"rh_buy_analysts": 10, "rh_total_analysts": 10, "rh_percent_buy": 100.0}, "ALEC": {"rh_buy_analysts": 10, "rh_total_analysts": 10, "rh_percent_buy": 100.0}, "ALGT": {"rh_buy_analysts": 11, "rh_total_analysts": 13, "rh_percent_buy": 84.62}, "ALK": {"rh_buy_analysts": 14, "rh_total_analysts": 15, "rh_percent_buy": 93.33}, "ALKT": {"rh_buy_analysts": 6, "rh_total_analysts": 7, "rh_percent_buy": 85.71}, "ALLO": {"rh_buy_analysts": 15, "rh_total_analysts": 16, "rh_percent_buy": 93.75}, "ALLY": {"rh_buy_analysts": 20, "rh_total_analysts": 21, "rh_percent_buy": 95.24}, "ALT": {"rh_buy_analysts": 7, "rh_total_analysts": 7, "rh_percent_buy": 100.0}, "ALXO": {"rh_buy_analysts": 8, "rh_total_analysts": 8, "rh_percent_buy": 100.0}, "AMRS": {"rh_buy_analysts": 6, "rh_total_analysts": 6, "rh_percent_buy": 100.0}, "APEI": {"rh_buy_analysts": 5, "rh_total_analysts": 6, "rh_percent_buy": 83.33}, "APLS": {"rh_buy_analysts": 14, "rh_total_analysts": 16, "rh_percent_buy": 87.5}, "APLT": {"rh_buy_analysts": 6, "rh_total_analysts": 7, "rh_percent_buy": 85.71}, "APTX": {"rh_buy_analysts": 9, "rh_total_analysts": 9, "rh_percent_buy": 100.0}, "ARNA": {"rh_buy_analysts": 16, "rh_total_analysts": 16, "rh_percent_buy": 100.0}, "ARQT": {"rh_buy_analysts": 8, "rh_total_analysts": 8, "rh_percent_buy": 100.0}, "ARVN": {"rh_buy_analysts": 14, "rh_total_analysts": 14, "rh_percent_buy": 100.0}, "ASPU": {"rh_buy_analysts": 6, "rh_total_analysts": 6, "rh_percent_buy": 100.0}, "ATEC": {"rh_buy_analysts": 8, "rh_total_analysts": 8, "rh_percent_buy": 100.0}, "ATRA": {"rh_buy_analysts": 9, "rh_total_analysts": 10, "rh_percent_buy": 90.0}, "ATRS": {"rh_buy_analysts": 7, "rh_total_analysts": 7, "rh_percent_buy": 100.0}, "ATSG": {"rh_buy_analysts": 6, "rh_total_analysts": 6, "rh_percent_buy": 100.0}, "ATVI": {"rh_buy_analysts": 31, "rh_total_analysts": 33, "rh_percent_buy": 93.94}, "AVAH": {"rh_buy_analysts": 10, "rh_total_analysts": 11, "rh_percent_buy": 90.91}, "AVRO": {"rh_buy_analysts": 8, "rh_total_analysts": 10, "rh_percent_buy": 80.0}, "AVXL": {"rh_buy_analysts": 6, "rh_total_analysts": 6, "rh_percent_buy": 100.0}, "AXSM": {"rh_buy_analysts": 12, "rh_total_analysts": 15, "rh_percent_buy": 80.0}, "AZEK": {"rh_buy_analysts": 12, "rh_total_analysts": 15, "rh_percent_buy": 80.0}, "BBIO": {"rh_buy_analysts": 9, "rh_total_analysts": 9, "rh_percent_buy": 100.0}, "BCEL": {"rh_buy_analysts": 10, "rh_total_analysts": 10, "rh_percent_buy": 100.0}, "BDSI": {"rh_buy_analysts": 8, "rh_total_analysts": 8, "rh_percent_buy": 100.0}, "BDTX": {"rh_buy_analysts": 7, "rh_total_analysts": 8, "rh_percent_buy": 87.5}, "BLND": {"rh_buy_analysts": 7, "rh_total_analysts": 8, "rh_percent_buy": 87.5}, "BMRN": {"rh_buy_analysts": 18, "rh_total_analysts": 22, "rh_percent_buy": 81.82}, "BTAI": {"rh_buy_analysts": 9, "rh_total_analysts": 9, "rh_percent_buy": 100.0}, "BTRS": {"rh_buy_analysts": 8, "rh_total_analysts": 9, "rh_percent_buy": 88.89}, "BYSI": {"rh_buy_analysts": 7, "rh_total_analysts": 7, "rh_percent_buy": 100.0}, "CABA": {"rh_buy_analysts": 6, "rh_total_analysts": 6, "rh_percent_buy": 100.0}, "CAMP": {"rh_buy_analysts": 5, "rh_total_analysts": 6, "rh_percent_buy": 83.33}, "CBAY": {"rh_buy_analysts": 10, "rh_total_analysts": 10, "rh_percent_buy": 100.0}, "CCCC": {"rh_buy_analysts": 5, "rh_total_analysts": 6, "rh_percent_buy": 83.33}, "CDNA": {"rh_buy_analysts": 5, "rh_total_analysts": 6, "rh_percent_buy": 83.33}, "CDTX": {"rh_buy_analysts": 6, "rh_total_analysts": 6, "rh_percent_buy": 100.0}, "CHGG": {"rh_buy_analysts": 14, "rh_total_analysts": 17, "rh_percent_buy": 82.35}, "CHRS": {"rh_buy_analysts": 6, "rh_total_analysts": 7, "rh_percent_buy": 85.71}, "CLAR": {"rh_buy_analysts": 6, "rh_total_analysts": 7, "rh_percent_buy": 85.71}, "CLDX": {"rh_buy_analysts": 6, "rh_total_analysts": 6, "rh_percent_buy": 100.0}, "CMBM": {"rh_buy_analysts": 8, "rh_total_analysts": 9, "rh_percent_buy": 88.89}, "CMCO": {"rh_buy_analysts": 8, "rh_total_analysts": 8, "rh_percent_buy": 100.0}, "CMRX": {"rh_buy_analysts": 6, "rh_total_analysts": 6, "rh_percent_buy": 100.0}, "CNCE": {"rh_buy_analysts": 6, "rh_total_analysts": 6, "rh_percent_buy": 100.0}, "COOK": {"rh_buy_analysts": 9, "rh_total_analysts": 10, "rh_percent_buy": 90.0}, "COUR": {"rh_buy_analysts": 14, "rh_total_analysts": 15, "rh_percent_buy": 93.33}, "COWN": {"rh_buy_analysts": 6, "rh_total_analysts": 7, "rh_percent_buy": 85.71}, "CSSE": {"rh_buy_analysts": 10, "rh_total_analysts": 10, "rh_percent_buy": 100.0}, "CSTL": {"rh_buy_analysts": 6, "rh_total_analysts": 6, "rh_percent_buy": 100.0}, "CTIC": {"rh_buy_analysts": 6, "rh_total_analysts": 6, "rh_percent_buy": 100.0}, "CTMX": {"rh_buy_analysts": 7, "rh_total_analysts": 8, "rh_percent_buy": 87.5}, "CURV": {"rh_buy_analysts": 7, "rh_total_analysts": 8, "rh_percent_buy": 87.5}, "CVET": {"rh_buy_analysts": 5, "rh_total_analysts": 6, "rh_percent_buy": 83.33}, "CVLT": {"rh_buy_analysts": 8, "rh_total_analysts": 9, "rh_percent_buy": 88.89}, "CYTK": {"rh_buy_analysts": 9, "rh_total_analysts": 10, "rh_percent_buy": 90.0}, "DAN": {"rh_buy_analysts": 9, "rh_total_analysts": 9, "rh_percent_buy": 100.0}, "DBRG": {"rh_buy_analysts": 5, "rh_total_analysts": 6, "rh_percent_buy": 83.33}, "DCPH": {"rh_buy_analysts": 11, "rh_total_analysts": 12, "rh_percent_buy": 91.67}, "DCT": {"rh_buy_analysts": 10, "rh_total_analysts": 11, "rh_percent_buy": 90.91}, "DMTK": {"rh_buy_analysts": 6, "rh_total_analysts": 6, "rh_percent_buy": 100.0}, "DRIO": {"rh_buy_analysts": 6, "rh_total_analysts": 7, "rh_percent_buy": 85.71}, "EEFT": {"rh_buy_analysts": 7, "rh_total_analysts": 7, "rh_percent_buy": 100.0}, "EGLE": {"rh_buy_analysts": 9, "rh_total_analysts": 10, "rh_percent_buy": 90.0}, "EHC": {"rh_buy_analysts": 13, "rh_total_analysts": 13, "rh_percent_buy": 100.0}, "EIGR": {"rh_buy_analysts": 6, "rh_total_analysts": 6, "rh_percent_buy": 100.0}, "ELMS": {"rh_buy_analysts": 7, "rh_total_analysts": 7, "rh_percent_buy": 100.0}, "ELY": {"rh_buy_analysts": 9, "rh_total_analysts": 11, "rh_percent_buy": 81.82}, "EQH": {"rh_buy_analysts": 10, "rh_total_analysts": 11, "rh_percent_buy": 90.91}, "ESTE": {"rh_buy_analysts": 6, "rh_total_analysts": 7, "rh_percent_buy": 85.71}, "ET": {"rh_buy_analysts": 18, "rh_total_analysts": 19, "rh_percent_buy": 94.74}, "ETNB": {"rh_buy_analysts": 8, "rh_total_analysts": 8, "rh_percent_buy": 100.0}, "EVER": {"rh_buy_analysts": 7, "rh_total_analysts": 8, "rh_percent_buy": 87.5}, "EXAS": {"rh_buy_analysts": 17, "rh_total_analysts": 20, "rh_percent_buy": 85.0}, "FA": {"rh_buy_analysts": 8, "rh_total_analysts": 8, "rh_percent_buy": 100.0}, "FBIO": {"rh_buy_analysts": 6, "rh_total_analysts": 6, "rh_percent_buy": 100.0}, "FIGS": {"rh_buy_analysts": 9, "rh_total_analysts": 11, "rh_percent_buy": 81.82}, "FISV": {"rh_buy_analysts": 27, "rh_total_analysts": 32, "rh_percent_buy": 84.38}, "FIXX": {"rh_buy_analysts": 9, "rh_total_analysts": 10, "rh_percent_buy": 90.0}, "FLWS": {"rh_buy_analysts": 7, "rh_total_analysts": 8, "rh_percent_buy": 87.5}, "FLXN": {"rh_buy_analysts": 9, "rh_total_analysts": 10, "rh_percent_buy": 90.0}, "FMTX": {"rh_buy_analysts": 7, "rh_total_analysts": 7, "rh_percent_buy": 100.0}, "FOUR": {"rh_buy_analysts": 8, "rh_total_analysts": 10, "rh_percent_buy": 80.0}, "FREE": {"rh_buy_analysts": 6, "rh_total_analysts": 6, "rh_percent_buy": 100.0}, "FRG": {"rh_buy_analysts": 6, "rh_total_analysts": 7, "rh_percent_buy": 85.71}, "FTAI": {"rh_buy_analysts": 11, "rh_total_analysts": 11, "rh_percent_buy": 100.0}, "FUBO": {"rh_buy_analysts": 6, "rh_total_analysts": 7, "rh_percent_buy": 85.71}, "FULC": {"rh_buy_analysts": 6, "rh_total_analysts": 7, "rh_percent_buy": 85.71}, "FUN": {"rh_buy_analysts": 8, "rh_total_analysts": 8, "rh_percent_buy": 100.0}, "GBIO": {"rh_buy_analysts": 7, "rh_total_analysts": 7, "rh_percent_buy": 100.0}, "GH": {"rh_buy_analysts": 14, "rh_total_analysts": 16, "rh_percent_buy": 87.5}, "GM": {"rh_buy_analysts": 23, "rh_total_analysts": 25, "rh_percent_buy": 92.0}, "GNK": {"rh_buy_analysts": 9, "rh_total_analysts": 10, "rh_percent_buy": 90.0}, "GNLN": {"rh_buy_analysts": 6, "rh_total_analysts": 6, "rh_percent_buy": 100.0}, "GOSS": {"rh_buy_analysts": 7, "rh_total_analysts": 8, "rh_percent_buy": 87.5}, "GPN": {"rh_buy_analysts": 27, "rh_total_analysts": 32, "rh_percent_buy": 84.38}, "GPRE": {"rh_buy_analysts": 9, "rh_total_analysts": 10, "rh_percent_buy": 90.0}, "GRWG": {"rh_buy_analysts": 8, "rh_total_analysts": 8, "rh_percent_buy": 100.0}, "GTES": {"rh_buy_analysts": 10, "rh_total_analysts": 12, "rh_percent_buy": 83.33}, "GTHX": {"rh_buy_analysts": 7, "rh_total_analysts": 8, "rh_percent_buy": 87.5}, "HALO": {"rh_buy_analysts": 10, "rh_total_analysts": 12, "rh_percent_buy": 83.33}, "HARP": {"rh_buy_analysts": 8, "rh_total_analysts": 9, "rh_percent_buy": 88.89}, "HCAT": {"rh_buy_analysts": 12, "rh_total_analysts": 12, "rh_percent_buy": 100.0}, "HEAR": {"rh_buy_analysts": 6, "rh_total_analysts": 6, "rh_percent_buy": 100.0}, "HIBB": {"rh_buy_analysts": 5, "rh_total_analysts": 6, "rh_percent_buy": 83.33}, "HLF": {"rh_buy_analysts": 6, "rh_total_analysts": 6, "rh_percent_buy": 100.0}, "HLMN": {"rh_buy_analysts": 8, "rh_total_analysts": 8, "rh_percent_buy": 100.0}, "HOOK": {"rh_buy_analysts": 6, "rh_total_analysts": 6, "rh_percent_buy": 100.0}, "HRTX": {"rh_buy_analysts": 6, "rh_total_analysts": 6, "rh_percent_buy": 100.0}, "HSC": {"rh_buy_analysts": 5, "rh_total_analysts": 6, "rh_percent_buy": 83.33}, "HWM": {"rh_buy_analysts": 9, "rh_total_analysts": 11, "rh_percent_buy": 81.82}, "HYFM": {"rh_buy_analysts": 6, "rh_total_analysts": 6, "rh_percent_buy": 100.0}, "HYZN": {"rh_buy_analysts": 6, "rh_total_analysts": 6, "rh_percent_buy": 100.0}, "ICAD": {"rh_buy_analysts": 7, "rh_total_analysts": 7, "rh_percent_buy": 100.0}, "IDYA": {"rh_buy_analysts": 8, "rh_total_analysts": 9, "rh_percent_buy": 88.89}, "IGMS": {"rh_buy_analysts": 8, "rh_total_analysts": 9, "rh_percent_buy": 88.89}, "IHRT": {"rh_buy_analysts": 8, "rh_total_analysts": 9, "rh_percent_buy": 88.89}, "IMUX": {"rh_buy_analysts": 8, "rh_total_analysts": 8, "rh_percent_buy": 100.0}, "INFI": {"rh_buy_analysts": 7, "rh_total_analysts": 7, "rh_percent_buy": 100.0}, "INSM": {"rh_buy_analysts": 8, "rh_total_analysts": 8, "rh_percent_buy": 100.0}, "INSW": {"rh_buy_analysts": 8, "rh_total_analysts": 9, "rh_percent_buy": 88.89}, "INTA": {"rh_buy_analysts": 8, "rh_total_analysts": 8, "rh_percent_buy": 100.0}, "JYNT": {"rh_buy_analysts": 5, "rh_total_analysts": 6, "rh_percent_buy": 83.33}, "KALV": {"rh_buy_analysts": 7, "rh_total_analysts": 7, "rh_percent_buy": 100.0}, "KDNY": {"rh_buy_analysts": 8, "rh_total_analysts": 8, "rh_percent_buy": 100.0}, "KNTE": {"rh_buy_analysts": 7, "rh_total_analysts": 7, "rh_percent_buy": 100.0}, "KRYS": {"rh_buy_analysts": 8, "rh_total_analysts": 8, "rh_percent_buy": 100.0}, "KURA": {"rh_buy_analysts": 8, "rh_total_analysts": 8, "rh_percent_buy": 100.0}, "KYMR": {"rh_buy_analysts": 8, "rh_total_analysts": 10, "rh_percent_buy": 80.0}, "KZR": {"rh_buy_analysts": 6, "rh_total_analysts": 6, "rh_percent_buy": 100.0}, "LAW": {"rh_buy_analysts": 8, "rh_total_analysts": 9, "rh_percent_buy": 88.89}, "LCTX": {"rh_buy_analysts": 5, "rh_total_analysts": 6, "rh_percent_buy": 83.33}, "LESL": {"rh_buy_analysts": 11, "rh_total_analysts": 13, "rh_percent_buy": 84.62}, "LEVI": {"rh_buy_analysts": 13, "rh_total_analysts": 13, "rh_percent_buy": 100.0}, "LGND": {"rh_buy_analysts": 7, "rh_total_analysts": 7, "rh_percent_buy": 100.0}, "LIFE": {"rh_buy_analysts": 6, "rh_total_analysts": 6, "rh_percent_buy": 100.0}, "LOGC": {"rh_buy_analysts": 6, "rh_total_analysts": 6, "rh_percent_buy": 100.0}, "LOVE": {"rh_buy_analysts": 7, "rh_total_analysts": 7, "rh_percent_buy": 100.0}, "LPRO": {"rh_buy_analysts": 10, "rh_total_analysts": 11, "rh_percent_buy": 90.91}, "LPSN": {"rh_buy_analysts": 15, "rh_total_analysts": 16, "rh_percent_buy": 93.75}, "LRN": {"rh_buy_analysts": 6, "rh_total_analysts": 7, "rh_percent_buy": 85.71}, "LUMO": {"rh_buy_analysts": 6, "rh_total_analysts": 6, "rh_percent_buy": 100.0}, "LUV": {"rh_buy_analysts": 20, "rh_total_analysts": 22, "rh_percent_buy": 90.91}, "MAPS": {"rh_buy_analysts": 6, "rh_total_analysts": 6, "rh_percent_buy": 100.0}, "MBUU": {"rh_buy_analysts": 9, "rh_total_analysts": 9, "rh_percent_buy": 100.0}, "MDGL": {"rh_buy_analysts": 12, "rh_total_analysts": 13, "rh_percent_buy": 92.31}, "MEIP": {"rh_buy_analysts": 8, "rh_total_analysts": 8, "rh_percent_buy": 100.0}, "MGNI": {"rh_buy_analysts": 9, "rh_total_analysts": 10, "rh_percent_buy": 90.0}, "MGTX": {"rh_buy_analysts": 7, "rh_total_analysts": 7, "rh_percent_buy": 100.0}, "MIRM": {"rh_buy_analysts": 7, "rh_total_analysts": 7, "rh_percent_buy": 100.0}, "MITK": {"rh_buy_analysts": 6, "rh_total_analysts": 6, "rh_percent_buy": 100.0}, "MKSI": {"rh_buy_analysts": 9, "rh_total_analysts": 11, "rh_percent_buy": 81.82}, "MP": {"rh_buy_analysts": 7, "rh_total_analysts": 8, "rh_percent_buy": 87.5}, "MRNS": {"rh_buy_analysts": 10, "rh_total_analysts": 10, "rh_percent_buy": 100.0}, "MRSN": {"rh_buy_analysts": 6, "rh_total_analysts": 7, "rh_percent_buy": 85.71}, "MRVI": {"rh_buy_analysts": 9, "rh_total_analysts": 9, "rh_percent_buy": 100.0}, "MTBC": {"rh_buy_analysts": 7, "rh_total_analysts": 7, "rh_percent_buy": 100.0}, "MTEM": {"rh_buy_analysts": 7, "rh_total_analysts": 8, "rh_percent_buy": 87.5}, "MTZ": {"rh_buy_analysts": 12, "rh_total_analysts": 13, "rh_percent_buy": 92.31}, "MU": {"rh_buy_analysts": 28, "rh_total_analysts": 33, "rh_percent_buy": 84.85}, "NARI": {"rh_buy_analysts": 5, "rh_total_analysts": 6, "rh_percent_buy": 83.33}, "NCR": {"rh_buy_analysts": 7, "rh_total_analysts": 8, "rh_percent_buy": 87.5}, "NESR": {"rh_buy_analysts": 7, "rh_total_analysts": 7, "rh_percent_buy": 100.0}, "NFE": {"rh_buy_analysts": 10, "rh_total_analysts": 11, "rh_percent_buy": 90.91}, "NGM": {"rh_buy_analysts": 6, "rh_total_analysts": 6, "rh_percent_buy": 100.0}, "NKTX": {"rh_buy_analysts": 6, "rh_total_analysts": 6, "rh_percent_buy": 100.0}, "NLTX": {"rh_buy_analysts": 7, "rh_total_analysts": 7, "rh_percent_buy": 100.0}, "NMIH": {"rh_buy_analysts": 9, "rh_total_analysts": 11, "rh_percent_buy": 81.82}, "NPTN": {"rh_buy_analysts": 9, "rh_total_analysts": 11, "rh_percent_buy": 81.82}, "NRIX": {"rh_buy_analysts": 7, "rh_total_analysts": 7, "rh_percent_buy": 100.0}, "NTLA": {"rh_buy_analysts": 14, "rh_total_analysts": 17, "rh_percent_buy": 82.35}, "NTRA": {"rh_buy_analysts": 9, "rh_total_analysts": 10, "rh_percent_buy": 90.0}, "NWSA": {"rh_buy_analysts": 8, "rh_total_analysts": 10, "rh_percent_buy": 80.0}, "OB": {"rh_buy_analysts": 5, "rh_total_analysts": 6, "rh_percent_buy": 83.33}, "OCDX": {"rh_buy_analysts": 9, "rh_total_analysts": 9, "rh_percent_buy": 100.0}, "OCUL": {"rh_buy_analysts": 6, "rh_total_analysts": 7, "rh_percent_buy": 85.71}, "OLO": {"rh_buy_analysts": 6, "rh_total_analysts": 6, "rh_percent_buy": 100.0}, "OMF": {"rh_buy_analysts": 12, "rh_total_analysts": 13, "rh_percent_buy": 92.31}, "ONEM": {"rh_buy_analysts": 12, "rh_total_analysts": 15, "rh_percent_buy": 80.0}, "OPFI": {"rh_buy_analysts": 5, "rh_total_analysts": 6, "rh_percent_buy": 83.33}, "ORIC": {"rh_buy_analysts": 7, "rh_total_analysts": 7, "rh_percent_buy": 100.0}, "OSH": {"rh_buy_analysts": 16, "rh_total_analysts": 18, "rh_percent_buy": 88.89}, "OSTK": {"rh_buy_analysts": 6, "rh_total_analysts": 6, "rh_percent_buy": 100.0}, "PASG": {"rh_buy_analysts": 9, "rh_total_analysts": 9, "rh_percent_buy": 100.0}, "PAYA": {"rh_buy_analysts": 10, "rh_total_analysts": 11, "rh_percent_buy": 90.91}, "PAYO": {"rh_buy_analysts": 6, "rh_total_analysts": 6, "rh_percent_buy": 100.0}, "PD": {"rh_buy_analysts": 8, "rh_total_analysts": 10, "rh_percent_buy": 80.0}, "PDSB": {"rh_buy_analysts": 6, "rh_total_analysts": 6, "rh_percent_buy": 100.0}, "PEGA": {"rh_buy_analysts": 12, "rh_total_analysts": 13, "rh_percent_buy": 92.31}, "PETQ": {"rh_buy_analysts": 6, "rh_total_analysts": 6, "rh_percent_buy": 100.0}, "PHAT": {"rh_buy_analysts": 5, "rh_total_analysts": 6, "rh_percent_buy": 83.33}, "PLL": {"rh_buy_analysts": 8, "rh_total_analysts": 8, "rh_percent_buy": 100.0}, "PMVP": {"rh_buy_analysts": 6, "rh_total_analysts": 7, "rh_percent_buy": 85.71}, "PRAX": {"rh_buy_analysts": 6, "rh_total_analysts": 6, "rh_percent_buy": 100.0}, "PRCH": {"rh_buy_analysts": 6, "rh_total_analysts": 6, "rh_percent_buy": 100.0}, "PRG": {"rh_buy_analysts": 7, "rh_total_analysts": 8, "rh_percent_buy": 87.5}, "PRIM": {"rh_buy_analysts": 6, "rh_total_analysts": 7, "rh_percent_buy": 85.71}, "PRPL": {"rh_buy_analysts": 9, "rh_total_analysts": 10, "rh_percent_buy": 90.0}, "PRVA": {"rh_buy_analysts": 8, "rh_total_analysts": 9, "rh_percent_buy": 88.89}, "PSNL": {"rh_buy_analysts": 7, "rh_total_analysts": 8, "rh_percent_buy": 87.5}, "PUBM": {"rh_buy_analysts": 9, "rh_total_analysts": 10, "rh_percent_buy": 90.0}, "PYPL": {"rh_buy_analysts": 39, "rh_total_analysts": 46, "rh_percent_buy": 84.78}, "QNST": {"rh_buy_analysts": 6, "rh_total_analysts": 6, "rh_percent_buy": 100.0}, "QTRX": {"rh_buy_analysts": 5, "rh_total_analysts": 6, "rh_percent_buy": 83.33}, "QTWO": {"rh_buy_analysts": 13, "rh_total_analysts": 15, "rh_percent_buy": 86.67}, "RAPT": {"rh_buy_analysts": 7, "rh_total_analysts": 7, "rh_percent_buy": 100.0}, "RCEL": {"rh_buy_analysts": 6, "rh_total_analysts": 7, "rh_percent_buy": 85.71}, "RCII": {"rh_buy_analysts": 7, "rh_total_analysts": 8, "rh_percent_buy": 87.5}, "RCKT": {"rh_buy_analysts": 12, "rh_total_analysts": 12, "rh_percent_buy": 100.0}, "RCM": {"rh_buy_analysts": 8, "rh_total_analysts": 8, "rh_percent_buy": 100.0}, "RCUS": {"rh_buy_analysts": 9, "rh_total_analysts": 10, "rh_percent_buy": 90.0}, "REGI": {"rh_buy_analysts": 12, "rh_total_analysts": 15, "rh_percent_buy": 80.0}, "REPL": {"rh_buy_analysts": 9, "rh_total_analysts": 9, "rh_percent_buy": 100.0}, "RETA": {"rh_buy_analysts": 9, "rh_total_analysts": 9, "rh_percent_buy": 100.0}, "RLAY": {"rh_buy_analysts": 6, "rh_total_analysts": 7, "rh_percent_buy": 85.71}, "RLMD": {"rh_buy_analysts": 6, "rh_total_analysts": 6, "rh_percent_buy": 100.0}, "RNA": {"rh_buy_analysts": 6, "rh_total_analysts": 6, "rh_percent_buy": 100.0}, "RNG": {"rh_buy_analysts": 22, "rh_total_analysts": 25, "rh_percent_buy": 88.0}, "RPAY": {"rh_buy_analysts": 10, "rh_total_analysts": 11, "rh_percent_buy": 90.91}, "RUN": {"rh_buy_analysts": 18, "rh_total_analysts": 21, "rh_percent_buy": 85.71}, "RVNC": {"rh_buy_analysts": 10, "rh_total_analysts": 10, "rh_percent_buy": 100.0}, "SAIL": {"rh_buy_analysts": 13, "rh_total_analysts": 14, "rh_percent_buy": 92.86}, "SEEL": {"rh_buy_analysts": 6, "rh_total_analysts": 6, "rh_percent_buy": 100.0}, "SELB": {"rh_buy_analysts": 7, "rh_total_analysts": 7, "rh_percent_buy": 100.0}, "SFT": {"rh_buy_analysts": 10, "rh_total_analysts": 11, "rh_percent_buy": 90.91}, "SGH": {"rh_buy_analysts": 6, "rh_total_analysts": 6, "rh_percent_buy": 100.0}, "SIBN": {"rh_buy_analysts": 7, "rh_total_analysts": 7, "rh_percent_buy": 100.0}, "SIEN": {"rh_buy_analysts": 7, "rh_total_analysts": 7, "rh_percent_buy": 100.0}, "SIOX": {"rh_buy_analysts": 6, "rh_total_analysts": 6, "rh_percent_buy": 100.0}, "SKYW": {"rh_buy_analysts": 5, "rh_total_analysts": 6, "rh_percent_buy": 83.33}, "SLM": {"rh_buy_analysts": 10, "rh_total_analysts": 12, "rh_percent_buy": 83.33}, "SMAR": {"rh_buy_analysts": 12, "rh_total_analysts": 15, "rh_percent_buy": 80.0}, "SNCY": {"rh_buy_analysts": 5, "rh_total_analysts": 6, "rh_percent_buy": 83.33}, "SNDX": {"rh_buy_analysts": 6, "rh_total_analysts": 7, "rh_percent_buy": 85.71}, "SPNE": {"rh_buy_analysts": 7, "rh_total_analysts": 7, "rh_percent_buy": 100.0}, "SRTS": {"rh_buy_analysts": 6, "rh_total_analysts": 6, "rh_percent_buy": 100.0}, "STOK": {"rh_buy_analysts": 8, "rh_total_analysts": 10, "rh_percent_buy": 80.0}, "STRO": {"rh_buy_analysts": 8, "rh_total_analysts": 8, "rh_percent_buy": 100.0}, "SURF": {"rh_buy_analysts": 6, "rh_total_analysts": 6, "rh_percent_buy": 100.0}, "SYBX": {"rh_buy_analysts": 6, "rh_total_analysts": 7, "rh_percent_buy": 85.71}, "SYRS": {"rh_buy_analysts": 8, "rh_total_analysts": 8, "rh_percent_buy": 100.0}, "TALO": {"rh_buy_analysts": 7, "rh_total_analysts": 7, "rh_percent_buy": 100.0}, "TBLA": {"rh_buy_analysts": 6, "rh_total_analysts": 6, "rh_percent_buy": 100.0}, "TCON": {"rh_buy_analysts": 5, "rh_total_analysts": 6, "rh_percent_buy": 83.33}, "TCRR": {"rh_buy_analysts": 8, "rh_total_analysts": 9, "rh_percent_buy": 88.89}, "TDUP": {"rh_buy_analysts": 9, "rh_total_analysts": 11, "rh_percent_buy": 81.82}, "TGTX": {"rh_buy_analysts": 7, "rh_total_analysts": 8, "rh_percent_buy": 87.5}, "TLMD": {"rh_buy_analysts": 5, "rh_total_analysts": 6, "rh_percent_buy": 83.33}, "TLS": {"rh_buy_analysts": 7, "rh_total_analysts": 7, "rh_percent_buy": 100.0}, "TMUS": {"rh_buy_analysts": 29, "rh_total_analysts": 33, "rh_percent_buy": 87.88}, "TNL": {"rh_buy_analysts": 9, "rh_total_analysts": 10, "rh_percent_buy": 90.0}, "TPTX": {"rh_buy_analysts": 10, "rh_total_analysts": 11, "rh_percent_buy": 90.91}, "TREE": {"rh_buy_analysts": 9, "rh_total_analysts": 9, "rh_percent_buy": 100.0}, "TSHA": {"rh_buy_analysts": 12, "rh_total_analysts": 12, "rh_percent_buy": 100.0}, "TSP": {"rh_buy_analysts": 11, "rh_total_analysts": 13, "rh_percent_buy": 84.62}, "TTMI": {"rh_buy_analysts": 6, "rh_total_analysts": 6, "rh_percent_buy": 100.0}, "TWLO": {"rh_buy_analysts": 28, "rh_total_analysts": 31, "rh_percent_buy": 90.32}, "UBER": {"rh_buy_analysts": 39, "rh_total_analysts": 43, "rh_percent_buy": 90.7}, "UCTT": {"rh_buy_analysts": 6, "rh_total_analysts": 6, "rh_percent_buy": 100.0}, "UPLD": {"rh_buy_analysts": 8, "rh_total_analysts": 8, "rh_percent_buy": 100.0}, "URGN": {"rh_buy_analysts": 5, "rh_total_analysts": 6, "rh_percent_buy": 83.33}, "UTI": {"rh_buy_analysts": 5, "rh_total_analysts": 6, "rh_percent_buy": 83.33}, "VIAV": {"rh_buy_analysts": 8, "rh_total_analysts": 10, "rh_percent_buy": 80.0}, "VKTX": {"rh_buy_analysts": 10, "rh_total_analysts": 10, "rh_percent_buy": 100.0}, "VRCA": {"rh_buy_analysts": 6, "rh_total_analysts": 6, "rh_percent_buy": 100.0}, "VRDN": {"rh_buy_analysts": 6, "rh_total_analysts": 6, "rh_percent_buy": 100.0}, "VRNT": {"rh_buy_analysts": 9, "rh_total_analysts": 9, "rh_percent_buy": 100.0}, "VSCO": {"rh_buy_analysts": 9, "rh_total_analysts": 11, "rh_percent_buy": 81.82}, "VST": {"rh_buy_analysts": 11, "rh_total_analysts": 12, "rh_percent_buy": 91.67}, "VSTO": {"rh_buy_analysts": 10, "rh_total_analysts": 10, "rh_percent_buy": 100.0}, "VYNE": {"rh_buy_analysts": 5, "rh_total_analysts": 6, "rh_percent_buy": 83.33}, "VZIO": {"rh_buy_analysts": 8, "rh_total_analysts": 9, "rh_percent_buy": 88.89}, "XFOR": {"rh_buy_analysts": 8, "rh_total_analysts": 8, "rh_percent_buy": 100.0}, "XGN": {"rh_buy_analysts": 6, "rh_total_analysts": 6, "rh_percent_buy": 100.0}, "XNCR": {"rh_buy_analysts": 11, "rh_total_analysts": 12, "rh_percent_buy": 91.67}, "YMAB": {"rh_buy_analysts": 7, "rh_total_analysts": 8, "rh_percent_buy": 87.5}, "ZD": {"rh_buy_analysts": 8, "rh_total_analysts": 10, "rh_percent_buy": 80.0}, "ZEN": {"rh_buy_analysts": 17, "rh_total_analysts": 19, "rh_percent_buy": 89.47}, "ZEV": {"rh_buy_analysts": 6, "rh_total_analysts": 7, "rh_percent_buy": 85.71}, "ZGNX": {"rh_buy_analysts": 10, "rh_total_analysts": 12, "rh_percent_buy": 83.33}, "ZIP": {"rh_buy_analysts": 5, "rh_total_analysts": 6, "rh_percent_buy": 83.33}, "ZNGA": {"rh_buy_analysts": 19, "rh_total_analysts": 20, "rh_percent_buy": 95.0}}