{"FA": {"rh_buy_analysts": 8, "rh_total_analysts": 8, "rh_percent_buy": 100.0, "yahoo_number_analysts": 8, "yahoo_percent_buys": 100.0, "yahoo_number_buy_analysts": 8}, "FLYW": {"rh_buy_analysts": 7, "rh_total_analysts": 7, "rh_percent_buy": 100.0, "yahoo_number_analysts": 10, "yahoo_percent_buys": 100.0, "yahoo_number_buy_analysts": 10}, "RIOT": {"rh_buy_analysts": 6, "rh_total_analysts": 6, "rh_percent_buy": 100.0, "yahoo_number_analysts": 7, "yahoo_percent_buys": 100.0, "yahoo_number_buy_analysts": 7}}